ios_battery/__init__.py
ios_battery/battery.py
ios_battery-1.0.6.dist-info/LICENSE
ios_battery-1.0.6.dist-info/METADATA
ios_battery-1.0.6.dist-info/WHEEL
ios_battery-1.0.6.dist-info/entry_points.txt
ios_battery-1.0.6.dist-info/top_level.txt
ios_battery-1.0.6.dist-info/RECORD
